twofa/__init__.py
twofa/auth.py
twofa/core.py
twofa-1.0.2.dist-info/LICENSE
twofa-1.0.2.dist-info/METADATA
twofa-1.0.2.dist-info/WHEEL
twofa-1.0.2.dist-info/top_level.txt
twofa-1.0.2.dist-info/RECORD
