Metadata-Version: 2.1
Name: twofa
Version: 1.0.2
Summary: TwoFa is a Python library designed to make two-factor authentication (2FA) integration seamless and secure for applications.
Home-page: https://github.com/finedevsam/two-fa
Author: Samson Ilemobayo
Author-email: Samson Ilemobayo <ilemobayosamson@gmail.com>
Maintainer-email: Samson Ilemobayo <ilemobayosamson@gmail.com>
License: GNU GENERAL PUBLIC LICENSE
Project-URL: Homepage, https://github.com/finedevsam/two-fa
Project-URL: Documentation, https://github.com/finedevsam/two-fa
Project-URL: Repository, https://github.com/finedevsam/two-fa.git
Project-URL: Bug Tracker, https://github.com/finedevsam/two-fa/issues
Keywords: security,2fa,twofa,authentication
Classifier: Development Status :: 4 - Beta
Classifier: Programming Language :: Python
Requires-Python: >=3.7
License-File: LICENSE
Requires-Dist: pyqrcode
Requires-Dist: qrcode
Requires-Dist: pyotp
Requires-Dist: boto3
Requires-Dist: pillow
Requires-Dist: cloudinary
Requires-Dist: wheel
